srivastav/__init__.py
srivastav/conversion.py
srivastav/middleware.py
srivastav/server_info.py
srivastav-0.0.3.dist-info/METADATA
srivastav-0.0.3.dist-info/WHEEL
srivastav-0.0.3.dist-info/top_level.txt
srivastav-0.0.3.dist-info/RECORD
