Metadata-Version: 2.1
Name: srivastav
Version: 0.0.3
Summary: Downalerts django Middleware 
Home-page: https://github.com/downalerts/django-logger
Author: Aman Srivastav
Author-email: amansrivastav.bytequests@gmail.com
License: BSD 2-clause
Classifier: Development Status :: 1 - Planning
Classifier: Intended Audience :: Science/Research
Classifier: License :: OSI Approved :: BSD License
Classifier: Operating System :: POSIX :: Linux
Classifier: Programming Language :: Python :: 3.5
Requires-Python: >=3.6
Requires-Dist: psutil (>=5.9.4)
